{
  "HP": 640,
  "HP+": 106,
  "HP5": 8,
  "HP5+": 0.7,
  "MP": 274,
  "MP+": 55,
  "MP5": 7.3,
  "MP5+": 0.45,
  "AD": 63,
  "AD+": 3,
  "AS": 0.645,
  "Ratio": 0.645,
  "AS+": "3.5%",
  "AR": 35,
  "AR+": 4.7,
  "MR": 32,
  "MR+": 2.05,
  "MS": 345,
  "Range": 175,
  "Q-DMG": "(27 * P_Q + 21 + 1.2 * Self_BoAD) * MOD_Phys",
  "W-DMG": "(35+45*P_W+1.2*Self_AD+0.65*Self_AP)*MOD_Phys*(1+0.33*Self_Crit)",
  "E-DMG": "(25+25*P_E+0.6*Self_AP)*MOD_Magic",
  "R-DMG": "(100*P_R-25+Self_BoAD+0.15*E_CHPV+1.1*Self_AP)*MOD_Phys",
  "P-DMG": 0,
  "Q-CD": "7.5-0.5*P_Q",
  "W-CD": "13-P_W",
  "E-CD": 11,
  "R-CD": "130 - 10 * P_R",
  "P-CD": 1,
  "Melee?": "TRUE",
  "img": {
    "centered": "XinZhao_0",
    "passive": "XinZhaoP",
    "QSpell": "XinZhaoQ",
    "WSpell": "XinZhaoW",
    "ESpell": "XinZhaoE",
    "RSpell": "XinZhaoR"
  },
  "Burst Calc": "IFERROR(__xludf.DUMMYFUNCTION(\"IF(OR(REGEXMATCH(FORMULATEXT(U149),\"\"HMOD\"\"),NOT(P_Q>0)),0,U149)+IF(OR(REGEXMATCH(FORMULATEXT(V149),\"\"HMOD\"\"),NOT(P_W>0)),0,V149)+IF(OR(REGEXMATCH(FORMULATEXT(W149),\"\"HMOD\"\"),NOT(P_E>0)),0,W149)+IF(OR(REGEXMATCH(FORMULATEXT(X149),\"\"HMOD\"\"),NOT(P_R>0)),0,X\"&\"149)+IF(REGEXMATCH(FORMULATEXT(Y149),\"\"HMOD\"\"),0,Y149)+Self_Proc_item+Self_Proc_Summ+Self_Proc_Rune+3*Self_DPS\"),0)",
  "Trade Calc": 0,
  "Energy": "FALSE",
  "No Mana": "FALSE"
}