{
  "HP": 655,
  "HP+": 99,
  "HP5": 7,
  "HP5+": 0.85,
  "MP": 450,
  "MP+": 60,
  "MP5": 6,
  "MP5+": 0.75,
  "AD": 50,
  "AD+": 3,
  "AS": 0.644,
  "Ratio": 0.644,
  "AS+": "3.4%",
  "AR": 27,
  "AR+": 4.7,
  "MR": 32,
  "MR+": 2.05,
  "MS": 330,
  "Range": 475,
  "Q-DMG": "(35+45*P_Q+0.7*Self_AP)*MOD_Magic",
  "W-DMG": "(22.5+7.5*P_W+Self_AP*0.3)*MOD_Magic",
  "E-DMG": "(50+20*P_E+0.8*Self_AP)*MOD_Magic",
  "R-DMG": 50.72463768,
  "P-DMG": 0,
  "Q-CD": "13-P_Q",
  "W-CD": "44-4*P_W",
  "E-CD": "12 - P_E",
  "R-CD": "150-P_R*10",
  "P-CD": 1,
  "Melee?": "FALSE",
  "img": {
    "centered": "Ivern_0",
    "passive": "IvernP",
    "QSpell": "IvernQ",
    "WSpell": "IvernW",
    "ESpell": "IvernE",
    "RSpell": "IvernR"
  },
  "Burst Calc": "IFERROR(__xludf.DUMMYFUNCTION(\"IF(OR(REGEXMATCH(FORMULATEXT(U46),\"\"HMOD\"\"),NOT(P_Q>0)),0,U46)+IF(OR(REGEXMATCH(FORMULATEXT(V46),\"\"HMOD\"\"),NOT(P_W>0)),0,V46)+IF(OR(REGEXMATCH(FORMULATEXT(W46),\"\"HMOD\"\"),NOT(P_E>0)),0,W46)+IF(OR(REGEXMATCH(FORMULATEXT(X46),\"\"HMOD\"\"),NOT(P_R>0)),0,X46)+IF(\"&\"REGEXMATCH(FORMULATEXT(Y46),\"\"HMOD\"\"),0,Y46)+Self_Proc_item+Self_Proc_Summ+Self_Proc_Rune+3*Self_DPS\"),378.639617918313)",
  "Trade Calc": 0,
  "Energy": "FALSE",
  "No Mana": "FALSE"
}