{
  "basicStats": {
    "Hp": 580.0,
    "hpLvl": 102.0,
    "AD": 55.0,
    "ADLvl": 3.0,
    "AS": 0.6399999856948853,
    "ASRatio": 0.6399999856948853,
    "Armor": 26.0,
    "ArmorLvl": 4.199999809265137,
    "MR": 30.0,
    "MRLvl": 1.2999999523162842,
    "MS": 325.0,
    "Lifesteal": 0,
    "Crit": 0,
    "CritDmg": 175,
    "HpRegen": 0.6499999761581421,
    "HpRegenLvl": 0.10999999940395355,
    "Mana": 348.0,
    "ManaLvl": 42.0,
    "AP": 0,
    "Range": 550.0,
    "ArmorPen": 0,
    "ResistPen": 0,
    "Haste": 0,
    "SpellVamp": 0,
    "ManaRegen": 1.2999999523162842,
    "ManaRegenLvl": 0.07999999821186066
  },
  "img": {
    "centered": "Aphelios_0",
    "passive": "ApheliosP",
    "QSpell": "ApheliosQ_ClientTooltipWrapper",
    "WSpell": "ApheliosW",
    "ESpell": "ApheliosE_ClientTooltipWrapper",
    "RSpell": "ApheliosR"
  },
  "spell": {
    "Passive": {
      "cd": 0,
      "damage": {
        "Bonus Attack Damage:": [
          4.5,
          9,
          13.5,
          18,
          22.5,
          27
        ],
        "Bonus Attack Speed:": [
          9,
          18,
          27,
          36,
          45,
          54
        ],
        "Lethality:": [
          5.5,
          11,
          16.5,
          22,
          27.5,
          33
        ]
      },
      "ratioAd": {
        "Bonus Attack Damage:": [
          0,
          0,
          0,
          0,
          0
        ],
        "Bonus Attack Speed:": [
          0,
          0,
          0,
          0,
          0
        ],
        "Lethality:": [
          0,
          0,
          0,
          0,
          0
        ]
      },
      "ratioAp": {
        "Bonus Attack Damage:": [
          0,
          0,
          0,
          0,
          0
        ],
        "Bonus Attack Speed:": [
          0,
          0,
          0,
          0,
          0
        ],
        "Lethality:": [
          0,
          0,
          0,
          0,
          0
        ]
      },
      "heal": [
        [
          0,
          0,
          0,
          0,
          0
        ]
      ],
      "ratioHealAd": [
        [
          0,
          0,
          0,
          0,
          0
        ]
      ],
      "ratioHealAp": [
        [
          0,
          0,
          0,
          0,
          0
        ]
      ],
      "shield": [
        [
          0,
          0,
          0,
          0,
          0
        ]
      ],
      "ratioShieldlAd": [
        [
          0,
          0,
          0,
          0,
          0
        ]
      ],
      "ratioShieldAp": [
        [
          0,
          0,
          0,
          0,
          0
        ]
      ],
      "bonusValue": [
        4.5,
        9,
        13.5,
        18,
        22.5,
        27
      ],
      "bonusRatioAD": [
        0,
        0,
        0,
        0,
        0
      ],
      "bonusRatioAP": [
        0,
        0,
        0,
        0,
        0
      ]
    },
    "Q": {
      "cd": 0,
      "basicStats": [
        {
          "damage": [
            0,
            0,
            0,
            0,
            0
          ],
          "ratioAd": [
            0,
            0,
            0,
            0,
            0
          ],
          "ratioAp": [
            0,
            0,
            0,
            0,
            0
          ],
          "heal": [
            [
              0,
              0,
              0,
              0,
              0
            ]
          ],
          "ratioHealAd": [
            [
              0,
              0,
              0,
              0,
              0
            ]
          ],
          "ratioHealAp": [
            [
              0,
              0,
              0,
              0,
              0
            ]
          ],
          "shield": [
            [
              0,
              0,
              0,
              0,
              0
            ]
          ],
          "ratioShieldlAd": [
            [
              0,
              0,
              0,
              0,
              0
            ]
          ],
          "ratioShieldAp": [
            [
              0,
              0,
              0,
              0,
              0
            ]
          ],
          "bonusValue": [
            [
              0,
              0,
              0,
              0,
              0
            ]
          ],
          "bonusRatioAD": [
            [
              0,
              0,
              0,
              0,
              0
            ]
          ],
          "bonusRatioAP": [
            [
              0,
              0,
              0,
              0,
              0
            ]
          ]
        }
      ]
    },
    "W": {
      "cd": [
        0.8
      ],
      "basicStats": [
        {
          "damage": [
            0,
            0,
            0,
            0,
            0
          ],
          "ratioAd": [
            0,
            0,
            0,
            0,
            0
          ],
          "ratioAp": [
            0,
            0,
            0,
            0,
            0
          ],
          "heal": [
            [
              0,
              0,
              0,
              0,
              0
            ]
          ],
          "ratioHealAd": [
            [
              0,
              0,
              0,
              0,
              0
            ]
          ],
          "ratioHealAp": [
            [
              0,
              0,
              0,
              0,
              0
            ]
          ],
          "shield": [
            [
              0,
              0,
              0,
              0,
              0
            ]
          ],
          "ratioShieldlAd": [
            [
              0,
              0,
              0,
              0,
              0
            ]
          ],
          "ratioShieldAp": [
            [
              0,
              0,
              0,
              0,
              0
            ]
          ],
          "bonusValue": [
            [
              0,
              0,
              0,
              0,
              0
            ]
          ],
          "bonusRatioAD": [
            [
              0,
              0,
              0,
              0,
              0
            ]
          ],
          "bonusRatioAP": [
            [
              0,
              0,
              0,
              0,
              0
            ]
          ]
        }
      ]
    },
    "E": {
      "cd": 0,
      "basicStats": [
        {
          "damage": [
            0,
            0,
            0,
            0,
            0
          ],
          "ratioAd": [
            0,
            0,
            0,
            0,
            0
          ],
          "ratioAp": [
            0,
            0,
            0,
            0,
            0
          ],
          "heal": [
            [
              0,
              0,
              0,
              0,
              0
            ]
          ],
          "ratioHealAd": [
            [
              0,
              0,
              0,
              0,
              0
            ]
          ],
          "ratioHealAp": [
            [
              0,
              0,
              0,
              0,
              0
            ]
          ],
          "shield": [
            [
              0,
              0,
              0,
              0,
              0
            ]
          ],
          "ratioShieldlAd": [
            [
              0,
              0,
              0,
              0,
              0
            ]
          ],
          "ratioShieldAp": [
            [
              0,
              0,
              0,
              0,
              0
            ]
          ],
          "bonusValue": [
            [
              0,
              0,
              0,
              0,
              0
            ]
          ],
          "bonusRatioAD": [
            [
              0,
              0,
              0,
              0,
              0
            ]
          ],
          "bonusRatioAP": [
            [
              0,
              0,
              0,
              0,
              0
            ]
          ]
        }
      ]
    },
    "R": {
      "cd": [
        120,
        110,
        100
      ],
      "basicStats": [
        {
          "damage": [
            0,
            0,
            0,
            0,
            0
          ],
          "ratioAd": [
            0,
            0,
            0,
            0,
            0
          ],
          "ratioAp": [
            0,
            0,
            0,
            0,
            0
          ],
          "heal": [
            [
              0,
              0,
              0,
              0,
              0
            ]
          ],
          "ratioHealAd": [
            [
              0,
              0,
              0,
              0,
              0
            ]
          ],
          "ratioHealAp": [
            [
              0,
              0,
              0,
              0,
              0
            ]
          ],
          "shield": [
            [
              0,
              0,
              0,
              0,
              0
            ]
          ],
          "ratioShieldlAd": [
            [
              0,
              0,
              0,
              0,
              0
            ]
          ],
          "ratioShieldAp": [
            [
              0,
              0,
              0,
              0,
              0
            ]
          ],
          "bonusValue": [
            [
              0,
              0,
              0,
              0,
              0
            ]
          ],
          "bonusRatioAD": [
            [
              0,
              0,
              0,
              0,
              0
            ]
          ],
          "bonusRatioAP": [
            [
              0,
              0,
              0,
              0,
              0
            ]
          ]
        }
      ]
    }
  }
}