{
  "basicStats": {
    "Hp": 605.0,
    "hpLvl": 88.0,
    "AD": 50.0,
    "ADLvl": 3.0,
    "AS": 0.625,
    "ASRatio": 0.625,
    "Armor": 32.0,
    "ArmorLvl": 5.0,
    "MR": 30.0,
    "MRLvl": 1.2999999523162842,
    "MS": 325.0,
    "Lifesteal": 0,
    "Crit": 0,
    "CritDmg": 175,
    "HpRegen": 0.5,
    "HpRegenLvl": 0.10000000149011612,
    "Mana": 425.0,
    "ManaLvl": 40.0,
    "AP": 0,
    "Range": 550.0,
    "ArmorPen": 0,
    "ResistPen": 0,
    "Haste": 0,
    "SpellVamp": 0,
    "ManaRegen": 2.299999952316284,
    "ManaRegenLvl": 0.07999999821186066
  },
  "img": {
    "centered": "Soraka_0",
    "passive": "Soraka_Passive",
    "QSpell": "SorakaQ",
    "WSpell": "SorakaW",
    "ESpell": "SorakaE",
    "RSpell": "SorakaR"
  },
  "spell": {
    "Passive": {
      "cd": "A DEFINIR",
      "damage": [
        0,
        0,
        0,
        0,
        0
      ],
      "ratioAd": [
        0,
        0,
        0,
        0,
        0
      ],
      "ratioAp": [
        0,
        0,
        0,
        0,
        0
      ],
      "heal": [
        [
          0,
          0,
          0,
          0,
          0
        ]
      ],
      "ratioHealAd": [
        [
          0,
          0,
          0,
          0,
          0
        ]
      ],
      "ratioHealAp": [
        [
          0,
          0,
          0,
          0,
          0
        ]
      ],
      "shield": [
        [
          0,
          0,
          0,
          0,
          0
        ]
      ],
      "ratioShieldlAd": [
        [
          0,
          0,
          0,
          0,
          0
        ]
      ],
      "ratioShieldAp": [
        [
          0,
          0,
          0,
          0,
          0
        ]
      ],
      "bonusValue": [
        [
          0,
          0,
          0,
          0,
          0
        ]
      ],
      "bonusRatioAD": [
        [
          0,
          0,
          0,
          0,
          0
        ]
      ],
      "bonusRatioAP": [
        [
          0,
          0,
          0,
          0,
          0
        ]
      ]
    },
    "Q": {
      "cd": [
        8,
        7,
        6,
        5,
        4
      ],
      "basicStats": [
        {
          "damage": [
            85,
            120,
            155,
            190,
            225
          ],
          "ratioAd": [
            0,
            0,
            0,
            0,
            0
          ],
          "ratioAp": [
            35
          ],
          "heal": [
            50,
            65,
            80,
            95,
            110
          ],
          "ratioHealAd": [
            0,
            0,
            0,
            0,
            0
          ],
          "ratioHealAp": [
            30
          ],
          "shield": [
            [
              0,
              0,
              0,
              0,
              0
            ]
          ],
          "ratioShieldlAd": [
            [
              0,
              0,
              0,
              0,
              0
            ]
          ],
          "ratioShieldAp": [
            [
              0,
              0,
              0,
              0,
              0
            ]
          ],
          "bonusValue": [
            20,
            22.5,
            25,
            27.5,
            30
          ],
          "bonusRatioAD": [
            0,
            0,
            0,
            0,
            0
          ],
          "bonusRatioAP": [
            0,
            0,
            0,
            0,
            0
          ]
        }
      ]
    },
    "W": {
      "cd": [
        6,
        5,
        4,
        3,
        2
      ],
      "basicStats": [
        {
          "damage": [
            0,
            0,
            0,
            0,
            0
          ],
          "ratioAd": [
            0,
            0,
            0,
            0,
            0
          ],
          "ratioAp": [
            0,
            0,
            0,
            0,
            0
          ],
          "heal": [
            90,
            110,
            130,
            150,
            170
          ],
          "ratioHealAd": [
            0,
            0,
            0,
            0,
            0
          ],
          "ratioHealAp": [
            50
          ],
          "shield": [
            [
              0,
              0,
              0,
              0,
              0
            ]
          ],
          "ratioShieldlAd": [
            [
              0,
              0,
              0,
              0,
              0
            ]
          ],
          "ratioShieldAp": [
            [
              0,
              0,
              0,
              0,
              0
            ]
          ],
          "bonusValue": [
            [
              0,
              0,
              0,
              0,
              0
            ]
          ],
          "bonusRatioAD": [
            [
              0,
              0,
              0,
              0,
              0
            ]
          ],
          "bonusRatioAP": [
            [
              0,
              0,
              0,
              0,
              0
            ]
          ]
        }
      ]
    },
    "E": {
      "cd": [
        20,
        19,
        18,
        17,
        16
      ],
      "basicStats": [
        {
          "damage": [
            140,
            190,
            240,
            290,
            340
          ],
          "ratioAd": [
            0,
            0,
            0,
            0,
            0
          ],
          "ratioAp": [
            80
          ],
          "heal": [
            [
              0,
              0,
              0,
              0,
              0
            ]
          ],
          "ratioHealAd": [
            [
              0,
              0,
              0,
              0,
              0
            ]
          ],
          "ratioHealAp": [
            [
              0,
              0,
              0,
              0,
              0
            ]
          ],
          "shield": [
            [
              0,
              0,
              0,
              0,
              0
            ]
          ],
          "ratioShieldlAd": [
            [
              0,
              0,
              0,
              0,
              0
            ]
          ],
          "ratioShieldAp": [
            [
              0,
              0,
              0,
              0,
              0
            ]
          ],
          "bonusValue": [
            [
              0,
              0,
              0,
              0,
              0
            ]
          ],
          "bonusRatioAD": [
            [
              0,
              0,
              0,
              0,
              0
            ]
          ],
          "bonusRatioAP": [
            [
              0,
              0,
              0,
              0,
              0
            ]
          ]
        }
      ]
    },
    "R": {
      "cd": [
        160,
        145,
        130
      ],
      "basicStats": [
        {
          "damage": [
            0,
            0,
            0,
            0,
            0
          ],
          "ratioAd": [
            0,
            0,
            0,
            0,
            0
          ],
          "ratioAp": [
            0,
            0,
            0,
            0,
            0
          ],
          "heal": [
            150,
            250,
            350
          ],
          "ratioHealAd": [
            0,
            0,
            0,
            0,
            0
          ],
          "ratioHealAp": [
            50
          ],
          "shield": [
            [
              0,
              0,
              0,
              0,
              0
            ]
          ],
          "ratioShieldlAd": [
            [
              0,
              0,
              0,
              0,
              0
            ]
          ],
          "ratioShieldAp": [
            [
              0,
              0,
              0,
              0,
              0
            ]
          ],
          "bonusValue": [
            [
              0,
              0,
              0,
              0,
              0
            ]
          ],
          "bonusRatioAD": [
            [
              0,
              0,
              0,
              0,
              0
            ]
          ],
          "bonusRatioAP": [
            [
              0,
              0,
              0,
              0,
              0
            ]
          ]
        }
      ]
    }
  }
}