{
  "basicStats": {
    "Hp": 655.0,
    "hpLvl": 102.0,
    "AD": 63.0,
    "ADLvl": 4.0,
    "AS": 0.625,
    "ASRatio": 0.625,
    "Armor": 36.0,
    "ArmorLvl": 5.449999809265137,
    "MR": 32.0,
    "MRLvl": 2.049999952316284,
    "MS": 330.0,
    "Lifesteal": 0,
    "Crit": 0,
    "CritDmg": 175,
    "HpRegen": 1.5,
    "HpRegenLvl": 0.14000000059604645,
    "Mana": 340.0,
    "ManaLvl": 45.0,
    "AP": 0,
    "Range": 350.0,
    "ArmorPen": 0,
    "ResistPen": 0,
    "Haste": 0,
    "SpellVamp": 0,
    "ManaRegen": 1.4500000476837158,
    "ManaRegenLvl": 0.1599999964237213
  },
  "img": {
    "centered": "Urgot_0",
    "passive": "Urgot_Passive",
    "QSpell": "UrgotQ",
    "WSpell": "UrgotW",
    "ESpell": "UrgotE",
    "RSpell": "UrgotR"
  },
  "spell": {
    "Passive": {
      "cd": 0,
      "damage": [
        0,
        0,
        0,
        0,
        0
      ],
      "ratioAd": [
        0,
        0,
        0,
        0,
        0
      ],
      "ratioAp": [
        0,
        0,
        0,
        0,
        0
      ],
      "heal": [
        [
          0,
          0,
          0,
          0,
          0
        ]
      ],
      "ratioHealAd": [
        [
          0,
          0,
          0,
          0,
          0
        ]
      ],
      "ratioHealAp": [
        [
          0,
          0,
          0,
          0,
          0
        ]
      ],
      "shield": [
        [
          0,
          0,
          0,
          0,
          0
        ]
      ],
      "ratioShieldlAd": [
        [
          0,
          0,
          0,
          0,
          0
        ]
      ],
      "ratioShieldAp": [
        [
          0,
          0,
          0,
          0,
          0
        ]
      ],
      "bonusValue": [
        [
          0,
          0,
          0,
          0,
          0
        ]
      ],
      "bonusRatioAD": [
        [
          0,
          0,
          0,
          0,
          0
        ]
      ],
      "bonusRatioAP": [
        [
          0,
          0,
          0,
          0,
          0
        ]
      ]
    },
    "Q": {
      "cd": [
        10,
        9.5,
        9,
        8.5,
        8
      ],
      "basicStats": [
        {
          "damage": [
            25,
            70,
            115,
            160,
            205
          ],
          "ratioAd": [
            70
          ],
          "ratioAp": [
            0,
            0,
            0,
            0,
            0
          ],
          "heal": [
            [
              0,
              0,
              0,
              0,
              0
            ]
          ],
          "ratioHealAd": [
            [
              0,
              0,
              0,
              0,
              0
            ]
          ],
          "ratioHealAp": [
            [
              0,
              0,
              0,
              0,
              0
            ]
          ],
          "shield": [
            [
              0,
              0,
              0,
              0,
              0
            ]
          ],
          "ratioShieldlAd": [
            [
              0,
              0,
              0,
              0,
              0
            ]
          ],
          "ratioShieldAp": [
            [
              0,
              0,
              0,
              0,
              0
            ]
          ],
          "bonusValue": [
            [
              0,
              0,
              0,
              0,
              0
            ]
          ],
          "bonusRatioAD": [
            [
              0,
              0,
              0,
              0,
              0
            ]
          ],
          "bonusRatioAP": [
            [
              0,
              0,
              0,
              0,
              0
            ]
          ]
        }
      ]
    },
    "W": {
      "cd": [
        12,
        9,
        6,
        3,
        0
      ],
      "basicStats": [
        {
          "damage": [
            0,
            0,
            0,
            0,
            0
          ],
          "ratioAd": [
            0,
            0,
            0,
            0,
            0
          ],
          "ratioAp": [
            0,
            0,
            0,
            0,
            0
          ],
          "heal": [
            [
              0,
              0,
              0,
              0,
              0
            ]
          ],
          "ratioHealAd": [
            [
              0,
              0,
              0,
              0,
              0
            ]
          ],
          "ratioHealAp": [
            [
              0,
              0,
              0,
              0,
              0
            ]
          ],
          "shield": [
            [
              0,
              0,
              0,
              0,
              0
            ]
          ],
          "ratioShieldlAd": [
            [
              0,
              0,
              0,
              0,
              0
            ]
          ],
          "ratioShieldAp": [
            [
              0,
              0,
              0,
              0,
              0
            ]
          ],
          "bonusValue": [
            [
              0,
              0,
              0,
              0,
              0
            ]
          ],
          "bonusRatioAD": [
            [
              0,
              0,
              0,
              0,
              0
            ]
          ],
          "bonusRatioAP": [
            [
              0,
              0,
              0,
              0,
              0
            ]
          ]
        }
      ]
    },
    "E": {
      "cd": [
        16,
        15.5,
        15,
        14.5,
        14
      ],
      "basicStats": [
        {
          "damage": [
            90,
            120,
            150,
            180,
            210
          ],
          "ratioAd": [
            100
          ],
          "ratioAp": [
            0,
            0,
            0,
            0,
            0
          ],
          "heal": [
            [
              0,
              0,
              0,
              0,
              0
            ]
          ],
          "ratioHealAd": [
            [
              0,
              0,
              0,
              0,
              0
            ]
          ],
          "ratioHealAp": [
            [
              0,
              0,
              0,
              0,
              0
            ]
          ],
          "shield": [
            55,
            75,
            95,
            115,
            135
          ],
          "ratioShieldlAd": [
            135
          ],
          "ratioShieldAp": [
            0,
            0,
            0,
            0,
            0
          ],
          "bonusValue": [
            [
              0,
              0,
              0,
              0,
              0
            ]
          ],
          "bonusRatioAD": [
            [
              0,
              0,
              0,
              0,
              0
            ]
          ],
          "bonusRatioAP": [
            [
              0,
              0,
              0,
              0,
              0
            ]
          ]
        }
      ]
    },
    "R": {
      "cd": [
        100,
        85,
        70
      ],
      "basicStats": [
        {
          "damage": [
            100,
            225,
            350
          ],
          "ratioAd": [
            50
          ],
          "ratioAp": [
            0,
            0,
            0,
            0,
            0
          ],
          "heal": [
            [
              0,
              0,
              0,
              0,
              0
            ]
          ],
          "ratioHealAd": [
            [
              0,
              0,
              0,
              0,
              0
            ]
          ],
          "ratioHealAp": [
            [
              0,
              0,
              0,
              0,
              0
            ]
          ],
          "shield": [
            [
              0,
              0,
              0,
              0,
              0
            ]
          ],
          "ratioShieldlAd": [
            [
              0,
              0,
              0,
              0,
              0
            ]
          ],
          "ratioShieldAp": [
            [
              0,
              0,
              0,
              0,
              0
            ]
          ],
          "bonusValue": [
            [
              0,
              0,
              0,
              0,
              0
            ]
          ],
          "bonusRatioAD": [
            [
              0,
              0,
              0,
              0,
              0
            ]
          ],
          "bonusRatioAP": [
            [
              0,
              0,
              0,
              0,
              0
            ]
          ]
        }
      ]
    }
  }
}